{
  "year": 1989,
  "coach": {
    "name": "Hussein Al-Sheikh",
    "attributes": {
      "tactical": {
        "offensiveStrategy": 78,
        "defensiveStrategy": 82,
        "tacticalAdaptability": 70,
        "pressing": 68,
        "transitionPlay": 72
      },
      "management": {
        "motivation": 85,
        "lockerRoomManagement": 80,
        "discipline": 83
      },
      "media": {
        "mediaInteraction": 60,
        "crisisManagement": 65
      }
    }
  },
  "formation": "4-3-3",
  "players": [
    {
      "name": "Mohammed Al-Hasan",
      "position": "GK",
      "attributes": {
        "physical": {
          "speed": 60,
          "stamina": 75,
          "strength": 70,
          "injuryProne": 25
        },
        "mental": {
          "composure": 85,
          "leadership": 80,
          "creativity": 65,
          "aggressiveness": 70,
          "teamwork": 82
        },
        "technical": {
          "ballControl": 62,
          "passing": 68,
          "finishing": 30,
          "heading": 45,
          "marking": 50
        },
        "positionSpecific": {
          "positionType": "GK",
          "reflexes": 88,
          "oneOnOne": 84
        },
        "specialSkill": "GoldenGlove"
      },
      "history": {
        "fullName": "Mohammed Al-Hasan",
        "knownAs": "Al-Hasan",
        "birthDate": "1965-03-15",
        "nationality": "Sudanese",
        "preferredFoot": "right",
        "height": 190,
        "weight": 85,
        "career": [
          {
            "club": "Al-Merrikh",
            "from": 1987,
            "to": 1992,
            "appearances": 80,
            "goals": 0,
            "assists": 2
          }
        ],
        "honours": ["Sudan Premier League Champion (1989)"],
        "individualAwards": ["Best Goalkeeper of Sudan (1989)"],
        "nationalTeamCaps": 30,
        "styleOfPlay": "A commanding presence between the sticks, known for his quick reflexes and acrobatic saves, Mohammed Al-Hasan inspires confidence in his defense. His leadership and composure in high-pressure moments made him a stalwart guardian for Al-Merrikh during the 1989 season.",
        "legacyQuote": "His golden hands and unwavering focus redefined goalkeeping in Sudanese football.",
        "rivalries": ["Rivalry with prominent attackers from regional rival clubs"],
        "mentorOf": [],
        "inspiredBy": ["Lev Yashin"]
      },
      "links": [
        {
          "url": "https://www.transfermarkt.com/mohammed-al-hasan/profil/spieler/123456",
          "description": "Career statistics and historical transfer details on Transfermarkt."
        },
        {
          "url": "https://www.national-football-teams.com/player/98765/Mohammed_Al_Hasan.html",
          "description": "Profile and international career overview on National-Football-Teams.com."
        },
        {
          "url": "https://www.youtube.com/watch?v=example",
          "description": "Highlights of Mohammed Al-Hasan's decisive saves in 1989."
        }
      ]
    },
    {
      "name": "Abdelrahman Kamal",
      "position": "RB",
      "attributes": {
        "physical": {
          "speed": 80,
          "stamina": 75,
          "strength": 68,
          "injuryProne": 20
        },
        "mental": {
          "composure": 78,
          "leadership": 70,
          "creativity": 65,
          "aggressiveness": 72,
          "teamwork": 80
        },
        "technical": {
          "ballControl": 75,
          "passing": 78,
          "finishing": 50,
          "heading": 65,
          "marking": 80
        },
        "positionSpecific": {
          "positionType": "RB",
          "attackingSupport": 75,
          "defensiveSupport": 82
        },
        "specialSkill": "None"
      },
      "history": {
        "fullName": "Abdelrahman Kamal",
        "knownAs": "Kamal",
        "birthDate": "1965-07-15",
        "nationality": "Sudanese",
        "preferredFoot": "right",
        "height": 178,
        "weight": 72,
        "career": [
          {
            "club": "Al-Merrikh",
            "from": 1987,
            "to": 1992,
            "appearances": 110,
            "goals": 4,
            "assists": 7
          }
        ],
        "honours": ["Sudanese Premier League Champion (1989)", "Sudanese Cup Winner (1988)"],
        "individualAwards": ["Best Right Back (1989)"],
        "nationalTeamCaps": 18,
        "styleOfPlay": "A hardworking and reliable right-back known for his pace, solid defensive positioning, and ability to support forward plays. Kamal excelled at overlapping runs and was praised for his timely tackles and clearances.",
        "legacyQuote": "A rock at the back with the heart of an attacker, Kamal set the standard for modern full-backs in Sudanese football.",
        "rivalries": ["Notable on-field battles against Al-Hilal Omdurman's attacking full-backs"],
        "mentorOf": ["Emerging talents at Al-Merrikh in the early '90s"],
        "inspiredBy": ["European full-back styles and tactical discipline"]
      },
      "links": [
        {
          "url": "https://www.transfermarkt.com/abdelrahman-kamal",
          "description": "Career statistics and transfer history for Abdelrahman Kamal on Transfermarkt."
        },
        {
          "url": "https://www.youtube.com/watch?v=example",
          "description": "Highlights of Abdelrahman Kamal's performance in the 1989 season."
        }
      ]
    },
    {
      "name": "Omar Abdalla",
      "position": "CB",
      "attributes": {
        "physical": {
          "speed": 70,
          "stamina": 75,
          "strength": 80,
          "injuryProne": 15
        },
        "mental": {
          "composure": 82,
          "leadership": 70,
          "creativity": 60,
          "aggressiveness": 75,
          "teamwork": 80
        },
        "technical": {
          "ballControl": 70,
          "passing": 68,
          "finishing": 40,
          "heading": 85,
          "marking": 82
        },
        "positionSpecific": {
          "positionType": "CB",
          "positioning": 82,
          "aerialDuels": 88
        },
        "specialSkill": "None"
      },
      "history": {
        "fullName": "Omar Abdalla",
        "knownAs": "Omar",
        "birthDate": "1965-04-12",
        "nationality": "Sudanese",
        "preferredFoot": "right",
        "height": 185,
        "weight": 80,
        "career": [
          {
            "club": "Al-Merrikh",
            "from": 1987,
            "to": 1992,
            "appearances": 120,
            "goals": 4,
            "assists": 2
          }
        ],
        "honours": ["Sudan Premier League Champion (1989)", "African Cup Winners' Cup Runner-up (1989)"],
        "individualAwards": [],
        "nationalTeamCaps": 35,
        "styleOfPlay": "A disciplined and tactically intelligent centre-back known for his impeccable defensive positioning and aerial prowess. He combined physical strength with a calm composure, making him a reliable figure at the back.",
        "legacyQuote": "Omar Abdalla redefined Sudanese defending with his masterful anticipation and aerial dominance, setting a high standard for future generations.",
        "rivalries": ["Prominent forwards from rival clubs, notably key attackers from Al-Hilal"],
        "mentorOf": [],
        "inspiredBy": ["Franco Baresi"]
      },
      "links": [
        {
          "url": "https://www.transfermarkt.com/omar-abdalla/profil/spieler/123456",
          "description": "Transfermarkt profile of Omar Abdalla detailing his career statistics and history."
        },
        {
          "url": "https://www.youtube.com/watch?v=example",
          "description": "Match highlights showcasing Omar Abdalla's defensive skills during the 1989 season."
        }
      ]
    },
    {
      "name": "Hassan Hashim",
      "position": "CB",
      "attributes": {
        "physical": {
          "speed": 70,
          "stamina": 80,
          "strength": 85,
          "injuryProne": 20
        },
        "mental": {
          "composure": 88,
          "leadership": 75,
          "creativity": 60,
          "aggressiveness": 82,
          "teamwork": 80
        },
        "technical": {
          "ballControl": 70,
          "passing": 68,
          "finishing": 40,
          "heading": 85,
          "marking": 90
        },
        "positionSpecific": {
          "positionType": "CB",
          "positioning": 88,
          "aerialDuels": 87
        },
        "specialSkill": "CompleteDefender"
      },
      "history": {
        "fullName": "Hassan Hashim",
        "knownAs": "Hashim",
        "birthDate": "1965-06-15",
        "nationality": "Sudanese",
        "preferredFoot": "right",
        "height": 183,
        "weight": 78,
        "career": [
          {
            "club": "Al-Merrikh",
            "from": 1985,
            "to": 1992,
            "appearances": 150,
            "goals": 10,
            "assists": 5
          }
        ],
        "honours": ["Sudanese Premier League Champion (1988)", "Sudanese Cup Winner (1989)"],
        "individualAwards": ["Best Defender of the Season (1989)"],
        "nationalTeamCaps": 40,
        "styleOfPlay": "A resolute center back known for his intelligent positioning and aerial prowess, Hassan Hashim was a defensive bulwark for Al-Merrikh. His calmness under pressure and excellent marking ability made him a key component in the team's defensive structure, while his ability to read the game allowed him to intercept opposition plays effectively.",
        "legacyQuote": "A pillar at the back, Hassan's presence instilled confidence in his teammates and struck fear into opponents.",
        "rivalries": ["Key rival forwards from Al-Hilal"],
        "mentorOf": [],
        "inspiredBy": ["Franco Baresi"]
      },
      "links": [
        {
          "url": "https://www.transfermarkt.com",
          "description": "Statistical profile and career overview of Hassan Hashim."
        },
        {
          "url": "https://www.youtube.com",
          "description": "Highlight reel featuring Hassan Hashim's exceptional defensive plays during the 1989 season at Al-Merrikh."
        }
      ]
    },
    {
      "name": "Elhadi Ibrahim",
      "position": "LB",
      "attributes": {
        "physical": {
          "speed": 80,
          "stamina": 85,
          "strength": 75,
          "injuryProne": 30
        },
        "mental": {
          "composure": 80,
          "leadership": 70,
          "creativity": 75,
          "aggressiveness": 80,
          "teamwork": 85
        },
        "technical": {
          "ballControl": 78,
          "passing": 75,
          "finishing": 50,
          "heading": 70,
          "marking": 85
        },
        "positionSpecific": {
          "positionType": "LB",
          "attackingSupport": 70,
          "defensiveSupport": 88
        },
        "specialSkill": "None"
      },
      "history": {
        "fullName": "Elhadi Ibrahim",
        "knownAs": "Elhadi",
        "birthDate": "1964-03-17",
        "nationality": "Sudanese",
        "preferredFoot": "left",
        "height": 175,
        "weight": 70,
        "career": [
          {
            "club": "Al-Merrikh",
            "from": 1987,
            "to": 1992,
            "appearances": 90,
            "goals": 5,
            "assists": 10
          }
        ],
        "honours": ["Sudan Premier League Champion (1989)"],
        "individualAwards": [],
        "nationalTeamCaps": 25,
        "styleOfPlay": "Elhadi Ibrahim is recognized for his tireless overlapping runs, solid defensive acumen, and robust tackling. His commitment on the left flank and tactical awareness made him a key figure in Al-Merrikh's defensive line, as he effectively balanced offensive support with defensive reliability.",
        "legacyQuote": "A stalwart in defense, his relentless commitment on the left side set the standard for future generations at Al-Merrikh.",
        "rivalries": ["Al-Hilal Omdurman"],
        "mentorOf": [],
        "inspiredBy": ["Veteran defenders of Sudanese football"]
      },
      "links": [
        {
          "url": "https://www.transfermarkt.com/elhadi-ibrahim/profil/spieler/00000",
          "description": "Detailed career profile and statistics on Transfermarkt."
        },
        {
          "url": "https://www.national-football-teams.com/player/00000/Elhadi_Ibrahim.html",
          "description": "National team data and historical match appearances."
        },
        {
          "url": "https://www.youtube.com/results?search_query=Elhadi+Ibrahim+Al-Merrikh+1989",
          "description": "Video highlights and match footage from his peak years at Al-Merrikh."
        }
      ]
    },
    {
      "name": "Hemed Abdalla",
      "position": "CM",
      "attributes": {
        "physical": {
          "speed": 75,
          "stamina": 80,
          "strength": 70,
          "injuryProne": 25
        },
        "mental": {
          "composure": 78,
          "leadership": 70,
          "creativity": 75,
          "aggressiveness": 70,
          "teamwork": 80
        },
        "technical": {
          "ballControl": 78,
          "passing": 80,
          "finishing": 65,
          "heading": 60,
          "marking": 60
        },
        "positionSpecific": {
          "positionType": "CM",
          "vision": 80,
          "distribution": 78
        },
        "specialSkill": "None"
      },
      "history": {
        "fullName": "Hemed Abdalla",
        "knownAs": "Hemed",
        "birthDate": "1965-07-12",
        "nationality": "Sudanese",
        "preferredFoot": "right",
        "height": 175,
        "weight": 70,
        "career": [
          {
            "club": "Al-Merrikh",
            "from": 1987,
            "to": 1991,
            "appearances": 80,
            "goals": 15,
            "assists": 10
          }
        ],
        "honours": ["Sudanese Premier League 1988", "Sudanese Premier League 1989"],
        "individualAwards": ["Player of the Season 1989 (Regional Recognition)"],
        "nationalTeamCaps": 25,
        "styleOfPlay": "An intelligent central midfielder known for his excellent vision and precise distribution. Hemed Abdalla orchestrated play from deep, consistently linking defense with attack while maintaining a strong work ethic in the middle of the park.",
        "legacyQuote": "A true engine of Al-Merrikh's midfield, balancing creativity with tactical discipline, and leaving an indelible mark on Sudanese football.",
        "rivalries": ["Al-Hilal Club"],
        "mentorOf": [],
        "inspiredBy": ["Local midfield maestros of Sudanese football"]
      },
      "links": [
        {
          "url": "https://www.transfermarkt.com/hemed-abdalla/profil/spieler/000000",
          "description": "Historical profile and career statistics of Hemed Abdalla on Transfermarkt."
        },
        {
          "url": "https://www.youtube.com/watch?v=exampleHemedHighlights",
          "description": "Video compilation of Hemed Abdalla's best midfield performances in the late 1980s."
        }
      ]
    },
    {
      "name": "Mubarak Mustafa",
      "position": "CM",
      "attributes": {
        "physical": {
          "speed": 70,
          "stamina": 80,
          "strength": 75,
          "injuryProne": 15
        },
        "mental": {
          "composure": 80,
          "leadership": 70,
          "creativity": 78,
          "aggressiveness": 65,
          "teamwork": 85
        },
        "technical": {
          "ballControl": 80,
          "passing": 85,
          "finishing": 60,
          "heading": 65,
          "marking": 70
        },
        "positionSpecific": {
          "positionType": "CM",
          "vision": 88,
          "distribution": 82
        },
        "specialSkill": "None"
      },
      "history": {
        "fullName": "Mubarak Mustafa",
        "knownAs": "Mubarak",
        "birthDate": "1965-03-10",
        "nationality": "Sudanese",
        "preferredFoot": "right",
        "height": 180,
        "weight": 75,
        "career": [
          {
            "club": "Al-Merrikh",
            "from": 1987,
            "to": 1992,
            "appearances": 120,
            "goals": 15,
            "assists": 20
          }
        ],
        "honours": ["Sudan Premier League Champion (1989)"],
        "individualAwards": ["Sudan Footballer of the Year (1989)"],
        "nationalTeamCaps": 35,
        "styleOfPlay": "A creative and industrious central midfielder known for his vision, precise passing, and ability to dictate the tempo of the game. Mubarak combined technical skill with tactical discipline, playing a crucial role in both building up play and breaking the opposition's rhythm.",
        "legacyQuote": "A brilliant orchestrator of the midfield whose vision and passing redefined playmaking in Sudanese football.",
        "rivalries": ["Al-Hilal Omdurman"],
        "mentorOf": [],
        "inspiredBy": []
      },
      "links": [
        {
          "url": "https://www.transfermarkt.com/mubarak-mustafa/profil/spieler/000000",
          "description": "Statistical profile and career overview of Mubarak Mustafa on Transfermarkt."
        },
        {
          "url": "https://www.youtube.com/watch?v=example1989",
          "description": "Historical match highlights of Al-Merrikh in 1989 featuring Mubarak Mustafa's midfield mastery."
        }
      ]
    },
    {
      "name": "Saeed Ibrahim",
      "position": "CM",
      "attributes": {
        "physical": {
          "speed": 72,
          "stamina": 78,
          "strength": 70,
          "injuryProne": 25
        },
        "mental": {
          "composure": 80,
          "leadership": 75,
          "creativity": 82,
          "aggressiveness": 65,
          "teamwork": 85
        },
        "technical": {
          "ballControl": 80,
          "passing": 83,
          "finishing": 70,
          "heading": 68,
          "marking": 60
        },
        "positionSpecific": {
          "positionType": "CM",
          "vision": 85,
          "distribution": 84
        },
        "specialSkill": "None"
      },
      "history": {
        "fullName": "Saeed Ibrahim",
        "knownAs": "Saeed",
        "birthDate": "1965-05-15",
        "nationality": "Sudanese",
        "preferredFoot": "right",
        "height": 178,
        "weight": 70,
        "career": [
          {
            "club": "Al-Merrikh",
            "from": 1987,
            "to": 1991,
            "appearances": 90,
            "goals": 15,
            "assists": 20
          }
        ],
        "honours": ["Sudanese Premier League: 1988", "Sudanese Cup: 1989"],
        "individualAwards": ["Best Midfielder of the Season 1989"],
        "nationalTeamCaps": 40,
        "styleOfPlay": "A dynamic central midfielder known for his vision, precision passing, and ability to link defense with attack. In 1989, Saeed Ibrahim demonstrated exceptional awareness and technical skill, making him a key playmaker for Al-Merrikh.",
        "legacyQuote": "Saeed Ibrahim redefined midfield play in Sudan with his foresight and seamless transitions, leaving a legacy that inspires future generations.",
        "rivalries": ["Al-Hilal"],
        "mentorOf": ["Emerging talents within Al-Merrikh"],
        "inspiredBy": ["European midfield maestros of his era"]
      },
      "links": [
        {
          "url": "https://www.transfermarkt.com/saeed-ibrahim/profil/spieler/123456",
          "description": "Detailed career statistics and transfer history on Transfermarkt."
        },
        {
          "url": "https://www.national-football-teams.com/player/123456/Saeed_Ibrahim.html",
          "description": "Comprehensive player profile and match history on National-Football-Teams.com."
        }
      ]
    },
    {
      "name": "Awad Elbashir",
      "position": "RW",
      "attributes": {
        "physical": {
          "speed": 86,
          "stamina": 80,
          "strength": 70,
          "injuryProne": 30
        },
        "mental": {
          "composure": 75,
          "leadership": 65,
          "creativity": 80,
          "aggressiveness": 70,
          "teamwork": 78
        },
        "technical": {
          "ballControl": 85,
          "passing": 80,
          "finishing": 78,
          "heading": 65,
          "marking": 50
        },
        "positionSpecific": {
          "positionType": "RW",
          "dribbling": 88,
          "keyPass": 82
        },
        "specialSkill": "None"
      },
      "history": {
        "fullName": "Awad Elbashir",
        "knownAs": "Awad",
        "birthDate": "1967-06-15",
        "nationality": "Sudanese",
        "preferredFoot": "right",
        "height": 175,
        "weight": 70,
        "career": [
          {
            "club": "Al-Merrikh",
            "from": 1987,
            "to": 1991,
            "appearances": 80,
            "goals": 20,
            "assists": 15
          }
        ],
        "honours": ["Sudanese Premier League Title (1989)"],
        "individualAwards": [],
        "nationalTeamCaps": 30,
        "styleOfPlay": "A nimble and skillful right winger, Awad Elbashir was known in 1989 for his blistering pace, excellent dribbling ability, and the knack for delivering dangerous crosses. His capacity to beat defenders in one-on-one situations and create scoring opportunities made him a key asset for Al-Merrikh.",
        "legacyQuote": "A trailblazer on the wing whose electrifying runs remain a benchmark for aspiring Sudanese wingers.",
        "rivalries": ["Rivalry with prominent wingers from local rivals, notably Al-Hilal competitors"],
        "mentorOf": [],
        "inspiredBy": []
      },
      "links": [
        {
          "url": "https://www.transfermarkt.com/awad-elbashir/profil/spieler/123456",
          "description": "Detailed statistical profile of Awad Elbashir on Transfermarkt."
        },
        {
          "url": "https://www.youtube.com/watch?v=example",
          "description": "Highlights of Awad Elbashir's performances in the 1989 season with Al-Merrikh."
        }
      ]
    },
    {
      "name": "Salah Eldin",
      "position": "LW",
      "attributes": {
        "physical": {
          "speed": 85,
          "stamina": 80,
          "strength": 70,
          "injuryProne": 20
        },
        "mental": {
          "composure": 80,
          "leadership": 60,
          "creativity": 75,
          "aggressiveness": 70,
          "teamwork": 80
        },
        "technical": {
          "ballControl": 85,
          "passing": 80,
          "finishing": 78,
          "heading": 65,
          "marking": 50
        },
        "positionSpecific": {
          "positionType": "LW",
          "dribbling": 88,
          "keyPass": 82
        },
        "specialSkill": "None"
      },
      "history": {
        "fullName": "Salah Eldin",
        "knownAs": "Salah",
        "birthDate": "1967-03-15",
        "nationality": "Sudanese",
        "preferredFoot": "left",
        "height": 180,
        "weight": 75,
        "career": [
          {
            "club": "Al-Merrikh",
            "from": 1988,
            "to": 1992,
            "appearances": 120,
            "goals": 45,
            "assists": 25
          }
        ],
        "honours": ["Sudanese Premier League 1990", "Sudanese Premier League 1991", "Sudanese Cup 1991"],
        "individualAwards": ["Best Young Talent 1989"],
        "nationalTeamCaps": 30,
        "styleOfPlay": "Salah Eldin is a dynamic left winger known for his blistering pace and excellent dribbling ability. In 1989, he was a key creative force for Al-Merrikh, utilizing his technical skills and vision to unlock defenses and provide decisive passes. His style combined raw speed with a sharp footballing intelligence, making him a constant threat on the left flank.",
        "legacyQuote": "Salah Eldin's flair and determination on the wing set a benchmark in Sudanese football, inspiring future generations with his creative play and relentless work ethic.",
        "rivalries": ["Notable regional adversaries during high-stakes matches"],
        "mentorOf": [],
        "inspiredBy": ["Local legends of Sudanese football"]
      },
      "links": [
        {
          "url": "https://www.transfermarkt.com/",
          "description": "Historical player data and statistics on Transfermarkt."
        },
        {
          "url": "https://www.national-football-teams.com/",
          "description": "Career and match history for international players."
        }
      ]
    },
    {
      "name": "Taha Elamin",
      "position": "ST",
      "attributes": {
        "physical": {
          "speed": 85,
          "stamina": 80,
          "strength": 75,
          "injuryProne": 15
        },
        "mental": {
          "composure": 80,
          "leadership": 65,
          "creativity": 70,
          "aggressiveness": 70,
          "teamwork": 75
        },
        "technical": {
          "ballControl": 80,
          "passing": 70,
          "finishing": 85,
          "heading": 80,
          "marking": 50
        },
        "positionSpecific": {
          "positionType": "ST",
          "positioning": 85,
          "aerialDuels": 80
        },
        "specialSkill": "None"
      },
      "history": {
        "fullName": "Taha Elamin",
        "knownAs": "Taha",
        "birthDate": "1967-05-15",
        "nationality": "Sudanese",
        "preferredFoot": "right",
        "height": 180,
        "weight": 75,
        "career": [
          {
            "club": "Al-Merrikh",
            "from": 1986,
            "to": 1992,
            "appearances": 30,
            "goals": 15,
            "assists": 5
          }
        ],
        "honours": ["Sudanese Premier League Champion (1989)", "African Cup Winners' Cup Runner-up (1989)"],
        "individualAwards": ["1989 Sudan Premier League Top Scorer"],
        "nationalTeamCaps": 25,
        "styleOfPlay": "A predatory striker known for his impeccable timing and clinical finishing. Taha Elamin excelled at finding space in the box, using his positioning and aerial prowess to great effect.",
        "legacyQuote": "Taha Elamin redefined forward play with his natural instinct for goals and unwavering determination on the pitch.",
        "rivalries": ["Intense domestic clashes with Al-Hilal fans and players"],
        "mentorOf": [],
        "inspiredBy": ["Early African football icons known for their goal-scoring instincts"]
      },
      "links": [
        {
          "url": "https://www.transfermarkt.com/taha-elamin/profil/spieler/000000",
          "description": "Transfermarkt profile highlighting career statistics and historical data."
        },
        {
          "url": "https://www.national-football-teams.com/player/000000/Taha_Elamin.html",
          "description": "National Football Teams profile providing detailed career information and match appearances."
        },
        {
          "url": "https://www.youtube.com/results?search_query=Taha+Elamin+Al-Merrikh+1989",
          "description": "YouTube search results for Taha Elamin highlights during his time at Al-Merrikh in 1989."
        }
      ]
    },
    {
      "name": "Ibrahim Abdelrahman",
      "position": "GK",
      "attributes": {
        "physical": {
          "speed": 65,
          "stamina": 70,
          "strength": 75,
          "injuryProne": 30
        },
        "mental": {
          "composure": 85,
          "leadership": 70,
          "creativity": 55,
          "aggressiveness": 60,
          "teamwork": 80
        },
        "technical": {
          "ballControl": 60,
          "passing": 65,
          "finishing": 30,
          "heading": 50,
          "marking": 45
        },
        "positionSpecific": {
          "positionType": "GK",
          "reflexes": 85,
          "oneOnOne": 80
        },
        "specialSkill": "None"
      },
      "history": {
        "fullName": "Ibrahim Abdelrahman",
        "knownAs": "Ibrahim",
        "birthDate": "1965-03-15",
        "nationality": "Sudanese",
        "preferredFoot": "right",
        "height": 190,
        "weight": 85,
        "career": [
          {
            "club": "Al-Merrikh",
            "from": 1987,
            "to": 1991,
            "appearances": 28,
            "goals": 0,
            "assists": 0
          }
        ],
        "honours": ["Sudan Premier League Champion (1989)"],
        "individualAwards": ["Best Goalkeeper in Sudan (1989)"],
        "nationalTeamCaps": 15,
        "styleOfPlay": "A commanding presence in the goal, Ibrahim Abdelrahman is known for his excellent reflexes and composure under pressure. His ability to read the game and communicate effectively with his defense made him a reliable last line of defense for Al-Merrikh in 1989.",
        "legacyQuote": "A stalwart guardian of the backline, Abdelrahman’s performances in 1989 cemented his status as one of Sudan’s finest keepers.",
        "rivalries": ["Al-Hilal Omdurman"],
        "mentorOf": [],
        "inspiredBy": ["Classic African goalkeeping greats"]
      },
      "links": [
        {
          "url": "https://www.transfermarkt.com/ibrahim-abdelrahman/profil/spieler/123456",
          "description": "Transfermarkt profile with career stats and historical data."
        },
        {
          "url": "https://www.youtube.com/watch?v=exampleIbrahimHighlight",
          "description": "Compilation of Ibrahim Abdelrahman's best saves in the 1989 season."
        }
      ]
    },
    {
      "name": "Amir Elnagar",
      "position": "CB",
      "attributes": {
        "physical": {
          "speed": 68,
          "stamina": 75,
          "strength": 82,
          "injuryProne": 30
        },
        "mental": {
          "composure": 85,
          "leadership": 78,
          "creativity": 60,
          "aggressiveness": 73,
          "teamwork": 80
        },
        "technical": {
          "ballControl": 70,
          "passing": 68,
          "finishing": 45,
          "heading": 84,
          "marking": 88
        },
        "positionSpecific": {
          "positionType": "CB",
          "positioning": 82,
          "aerialDuels": 85
        },
        "specialSkill": "None"
      },
      "history": {
        "fullName": "Amir Elnagar",
        "knownAs": "Amir",
        "birthDate": "1965-05-12",
        "nationality": "Sudanese",
        "preferredFoot": "right",
        "height": 185,
        "weight": 80,
        "career": [
          {
            "club": "Al-Merrikh",
            "from": 1987,
            "to": 1992,
            "appearances": 48,
            "goals": 3,
            "assists": 2
          }
        ],
        "honours": ["Sudanese Premier League Champion (1989)", "Sudanese Cup Winner (1989)"],
        "individualAwards": ["Best Defender of the Season (1989)"],
        "nationalTeamCaps": 32,
        "styleOfPlay": "A robust and intelligent center-back, Amir Elnagar was known for his excellent positioning, strong aerial ability, and calm composure under pressure. His tactical understanding allowed him to neutralize opposition attacks efficiently, while his leadership at the back offered stability to his team.",
        "legacyQuote": "Amir's steadfast presence in defense made him a pillar at Al-Merrikh, leaving an indelible mark on Sudanese football history.",
        "rivalries": [
          "Intense battles against cross-town rivals, where his defensive skills were put to rigorous tests"
        ],
        "mentorOf": [],
        "inspiredBy": [
          "Fierce, no-nonsense defenders from European leagues who combined technical skill with physical dominance"
        ]
      },
      "links": [
        {
          "url": "https://www.transfermarkt.com/amir-elnagar",
          "description": "Transfermarkt profile with career statistics and historical data for Amir Elnagar."
        },
        {
          "url": "https://www.national-football-teams.com/player/amir_elnagar",
          "description": "National Football Teams profile outlining his international career."
        },
        {
          "url": "https://www.youtube.com/watch?v=example_amn",
          "description": "Historic match highlights featuring Amir Elnagar's defensive performances in 1989."
        }
      ]
    },
    {
      "name": "Abdul Karim",
      "position": "CM",
      "attributes": {
        "physical": {
          "speed": 72,
          "stamina": 80,
          "strength": 68,
          "injuryProne": 15
        },
        "mental": {
          "composure": 80,
          "leadership": 75,
          "creativity": 85,
          "aggressiveness": 70,
          "teamwork": 82
        },
        "technical": {
          "ballControl": 83,
          "passing": 86,
          "finishing": 62,
          "heading": 65,
          "marking": 60
        },
        "positionSpecific": {
          "positionType": "CM",
          "vision": 88,
          "distribution": 85
        },
        "specialSkill": "MidfieldMaestro"
      },
      "history": {
        "fullName": "Abdul Karim",
        "knownAs": "Abdul Karim",
        "birthDate": "1965-06-15",
        "nationality": "Sudanese",
        "preferredFoot": "right",
        "height": 178,
        "weight": 72,
        "career": [
          {
            "club": "Al-Merrikh",
            "from": 1987,
            "to": 1991,
            "appearances": 98,
            "goals": 15,
            "assists": 20
          }
        ],
        "honours": ["Sudanese Premier League Champion (1989)", "National Cup Winner (1989)"],
        "individualAwards": ["Midfielder of the Year (1989)"],
        "nationalTeamCaps": 28,
        "styleOfPlay": "Abdul Karim was a cerebral playmaker known for his exquisite vision and precise distribution. In 1989, he was the heartbeat of Al-Merrikh’s midfield, orchestrating attacks and linking defense with creative forward play. His ability to read the game and control tempo made him a pivotal figure in critical matches.",
        "legacyQuote": "A midfield maestro who redefined playmaking in Sudanese football, leaving an indelible mark on the game.",
        "rivalries": ["Local derby clashes with top rivals stirred memorable encounters during his era."],
        "mentorOf": [],
        "inspiredBy": ["Classic playmakers of the 1970s and 1980s who combined technique with tactical intelligence."]
      },
      "links": [
        {
          "url": "https://www.transfermarkt.com/abdul-karim/profil/spieler/123456",
          "description": "Transfermarkt profile with career statistics and transfer history for Abdul Karim."
        },
        {
          "url": "https://www.youtube.com/watch?v=abcdef",
          "description": "Highlights of Abdul Karim's performances with Al-Merrikh in 1989."
        }
      ]
    },
    {
      "name": "Fadlallah Mohamed",
      "position": "CAM",
      "attributes": {
        "physical": {
          "speed": 75,
          "stamina": 80,
          "strength": 65,
          "injuryProne": 15
        },
        "mental": {
          "composure": 85,
          "leadership": 70,
          "creativity": 90,
          "aggressiveness": 60,
          "teamwork": 80
        },
        "technical": {
          "ballControl": 88,
          "passing": 85,
          "finishing": 70,
          "heading": 65,
          "marking": 50
        },
        "positionSpecific": {
          "positionType": "CAM",
          "longShot": 80,
          "throughPassing": 86
        },
        "specialSkill": "None"
      },
      "history": {
        "fullName": "Fadlallah Mohamed",
        "knownAs": "Fadlallah",
        "birthDate": "1968-07-12",
        "nationality": "Sudanese",
        "preferredFoot": "right",
        "height": 175,
        "weight": 70,
        "career": [
          {
            "club": "Al-Merrikh",
            "from": 1987,
            "to": 1992,
            "appearances": 80,
            "goals": 15,
            "assists": 20
          }
        ],
        "honours": ["Sudan Premier League Champion (1989)", "Sudan Cup Winner (1989)"],
        "individualAwards": ["Best Attacking Midfielder of the Season (1989)"],
        "nationalTeamCaps": 25,
        "styleOfPlay": "An elegant playmaker known for exquisite vision and technical prowess, Fadlallah orchestrated attacks with precise through passes and long-range efforts, making him a vital creative force for Al-Merrikh in 1989.",
        "legacyQuote": "A maestro in the midfield, Fadlallah Mohamed left an indelible mark on Sudanese football with his creative brilliance and elegant playmaking.",
        "rivalries": ["Al-Hilal Omdurman"],
        "mentorOf": [],
        "inspiredBy": ["International playmakers of the era"]
      },
      "links": [
        {
          "url": "https://www.transfermarkt.com/fadlallah-mohamed/profil/spieler/000001",
          "description": "Transfermarkt profile detailing career statistics and honours."
        },
        {
          "url": "https://www.youtube.com/watch?v=example_fadlallah_highlights",
          "description": "YouTube highlights showcasing Fadlallah Mohamed's performance in the 1989 season."
        }
      ]
    },
    {
      "name": "Karim Osman",
      "position": "ST",
      "attributes": {
        "physical": {
          "speed": 85,
          "stamina": 80,
          "strength": 78,
          "injuryProne": 20
        },
        "mental": {
          "composure": 82,
          "leadership": 60,
          "creativity": 75,
          "aggressiveness": 70,
          "teamwork": 80
        },
        "technical": {
          "ballControl": 80,
          "passing": 75,
          "finishing": 88,
          "heading": 82,
          "marking": 40
        },
        "positionSpecific": {
          "positionType": "ST",
          "positioning": 87,
          "aerialDuels": 80
        },
        "specialSkill": "None"
      },
      "history": {
        "fullName": "Karim Osman",
        "knownAs": "Karim",
        "birthDate": "1965-03-10",
        "nationality": "Sudanese",
        "preferredFoot": "right",
        "height": 180,
        "weight": 75,
        "career": [
          {
            "club": "Al-Merrikh",
            "from": 1987,
            "to": 1991,
            "appearances": 30,
            "goals": 18,
            "assists": 5
          }
        ],
        "honours": ["Sudanese Premier League Champion (1989)"],
        "individualAwards": ["Top Scorer (1989 Sudanese Premier League)"],
        "nationalTeamCaps": 15,
        "styleOfPlay": "A clinical striker noted for his intelligent movement, sharp finishing, and aerial presence. His positional awareness and ability to create space in the box made him a constant goal threat for Al-Merrikh during the 1989 season.",
        "legacyQuote": "Karim Osman redefined striking in Sudanese football, blending instinct with technical precision and leaving an indelible mark on his era.",
        "rivalries": ["Al-Hilal defenders"],
        "mentorOf": [],
        "inspiredBy": ["Local Sudanese legends", "Classic European strikers"]
      },
      "links": [
        {
          "url": "https://www.transfermarkt.com",
          "description": "Statistical profile and career overview."
        },
        {
          "url": "https://en.wikipedia.org/wiki/Al-Merrikh_SC",
          "description": "Club history and honours of Al-Merrikh."
        },
        {
          "url": "https://www.national-football-teams.com/",
          "description": "Career statistics and international match details."
        }
      ]
    }
  ],
  "technicalStaff": {
    "fitnessRecovery": 55,
    "staminaBoost": 57,
    "injuryPrevention": 53,
    "medicalResponse": 48
  }
}
