{
  "foundationDate": "October 4, 1945",
  "city": "Belgrade",
  "fullName": "Fudbalski klub Partizan",
  "shortName": "FK Partizan",
  "stadium": {
    "name": "Partizan Stadium",
    "capacity": 29775
  },
  "socialMedia": {
    "instagram": "https://www.instagram.com/fkpartizan",
    "tiktok": "https://www.tiktok.com/@fkpartizan"
  },
  "colors": {
    "home": {
      "bgColor": "rgb(0, 0, 0)",
      "fontColor": "rgb(255, 255, 255)"
    },
    "away": {
      "bgColor": "rgb(255, 255, 255)",
      "fontColor": "rgb(0, 0, 0)"
    },
    "alternate": {
      "bgColor": "rgb(255, 0, 0)",
      "fontColor": "rgb(255, 255, 255)"
    }
  }
}
